[{"orientacion":"Heterosexual","genero":"Hombre","telefono":314159265357278,"mascota":"Perros","signo":"Virgo","entretenimiento":"Videojuegos","pasatiempo":"Interior(Cines, en casa, etc.)","personalidad":"Introvertido","peliculas":"MCU(Marvel)","comida":"Dulces","loteria":"Invertirlo","bebida":"Soda","b_alcoholica":"(Ron, vodka, Tequila, singani) y sus cocteles","viaje":"Asia","musica":"Rock espa\u00f1ol\/ingles","prioridad_pareja":"Dinero\/estatus social","terapia":"Entretenimiento(Peliculas, series, musica)","nombre":"gigachad"},{"orientacion":"Heterosexual","genero":"Hombre","telefono":68969696,"mascota":"Perros","signo":"Libra","entretenimiento":"Videojuegos","pasatiempo":"Interior(Cines, en casa, etc.)","personalidad":"Extrovertido pero timido","peliculas":"MCU(Marvel)","comida":"Dulces","loteria":"Gastarlo en familia y en ti","bebida":"Soda","b_alcoholica":"Cerveza","viaje":"Asia","musica":"Pop en ingles","prioridad_pareja":"Sentido del humor","terapia":"Entretenimiento(Peliculas, series, musica)","nombre":"Nicolas Cari"},{"orientacion":"Heterosexual","genero":"Hombre","telefono":72849649,"mascota":"Perros","signo":"Geminis","entretenimiento":"Peliculas","pasatiempo":"Interior(Cines, en casa, etc.)","personalidad":"Introvertido pero abierto a nuevas experiencias","peliculas":"MCU(Marvel)","comida":"Salado","loteria":"Gastarlo en familia y en ti","bebida":"Cafe","b_alcoholica":"Licores dulces(Jagger, 3 plumas, goss cake, etc)","viaje":"Asia","musica":"Pop latino\/reguet\u00f3n","prioridad_pareja":"Limpieza","terapia":"Ejercicio","nombre":"gabriel balderrama"},{"orientacion":"Homosexual","genero":"Hombre","telefono":1,"mascota":"Reptiles","signo":"Aries","entretenimiento":"Series","pasatiempo":"Exterior(Parques, restaurantes, etc.)","personalidad":"Introvertido","peliculas":"Distopica juvenil(Juegos del hambre, maze runner, etc)","comida":"No tengo preferencia","loteria":"Gastarlo en familia y en ti","bebida":"Soda","b_alcoholica":"Guarapo","viaje":"Europa","musica":"Rock espa\u00f1ol\/ingles","prioridad_pareja":"Sentido del humor","terapia":"Busco alguien para desahogarme","nombre":"1"},{"orientacion":"Heterosexual","genero":"Hombre","telefono":1,"mascota":"Gatos","signo":"Aries","entretenimiento":"Series","pasatiempo":"Exterior(Parques, restaurantes, etc.)","personalidad":"Introvertido","peliculas":"Piratas del caribe","comida":"Dulces","loteria":"Viajar por el mundo","bebida":"Cafe","b_alcoholica":"Guarapo","viaje":"Europa","musica":"Pop latino\/reguet\u00f3n","prioridad_pareja":"Limpieza","terapia":"Entretenimiento(Peliculas, series, musica)","nombre":"2"},{"orientacion":"Heterosexual","genero":"Mujer","telefono":1,"mascota":"Aves","signo":"Libra","entretenimiento":"Peliculas","pasatiempo":"Interior(Cines, en casa, etc.)","personalidad":"Extrovertido pero timido","peliculas":"MCU(Marvel)","comida":"Salado","loteria":"Invertirlo","bebida":"Agua","b_alcoholica":"Licores dulces(Jagger, 3 plumas, goss cake, etc)","viaje":"Europa","musica":"Alternativa\/Indie","prioridad_pareja":"Dinero\/estatus social","terapia":"Entretenimiento(Peliculas, series, musica)","nombre":"3"},{"orientacion":"Heterosexual","genero":"Mujer","telefono":1,"mascota":"Gatos","signo":"Acuario","entretenimiento":"Series","pasatiempo":"Interior(Cines, en casa, etc.)","personalidad":"Introvertido","peliculas":"Piratas del caribe","comida":"Dulces","loteria":"Gastarlo en familia y en ti","bebida":"Cafe","b_alcoholica":"(Ron, vodka, Tequila, singani) y sus cocteles","viaje":"Estados unidos","musica":"Alternativa\/Indie","prioridad_pareja":"Sentido del humor","terapia":"Como mis penas","nombre":"4"},{"orientacion":"Heterosexual","genero":"Mujer","telefono":1,"mascota":"Gatos","signo":"Cancer","entretenimiento":"Series","pasatiempo":"Interior(Cines, en casa, etc.)","personalidad":"Extrovertido","peliculas":"Piratas del caribe","comida":"Dulces","loteria":"Hacer fiestas grandes","bebida":"Cafe","b_alcoholica":"Vino","viaje":"Europa","musica":"Cumbiones\/Nacional","prioridad_pareja":"Fisico","terapia":"Busco alguien para desahogarme","nombre":"5"},{"orientacion":"Homosexual","genero":"Hombre","telefono":1,"mascota":"Mucha responsabilidad","signo":"Escorpio","entretenimiento":"Series","pasatiempo":"Exterior(Parques, restaurantes, etc.)","personalidad":"Introvertido pero abierto a nuevas experiencias","peliculas":"Star wars","comida":"No tengo preferencia","loteria":"Invertirlo","bebida":"Jugos de fruta","b_alcoholica":"Licores dulces(Jagger, 3 plumas, goss cake, etc)","viaje":"Europa","musica":"Pop latino\/reguet\u00f3n","prioridad_pareja":"Dinero\/estatus social","terapia":"Busco alguien para desahogarme","nombre":"6"},{"orientacion":"Heterosexual","genero":"Hombre","telefono":1,"mascota":"Aves","signo":"Capricornio","entretenimiento":"Videojuegos","pasatiempo":"Exterior(Parques, restaurantes, etc.)","personalidad":"Introvertido pero abierto a nuevas experiencias","peliculas":"MCU(Marvel)","comida":"Salado","loteria":"Hacer caridad","bebida":"Agua","b_alcoholica":"No tomo","viaje":"Europa","musica":"Pop latino\/reguet\u00f3n","prioridad_pareja":"Madurez","terapia":"Vivo con el dolor","nombre":"7"},{"orientacion":"Heterosexual","genero":"Hombre","telefono":1,"mascota":"Perros","signo":"Virgo","entretenimiento":"Series","pasatiempo":"Exterior(Parques, restaurantes, etc.)","personalidad":"Extrovertido pero timido","peliculas":"Harry potter","comida":"Salado","loteria":"Hacer fiestas grandes","bebida":"Te","b_alcoholica":"Cerveza","viaje":"Asia","musica":"Rock espa\u00f1ol\/ingles","prioridad_pareja":"Fisico","terapia":"Como mis penas","nombre":"8"},{"orientacion":"Homosexual","genero":"Mujer","telefono":1,"mascota":"Mucha responsabilidad","signo":"Escorpio","entretenimiento":"Libros","pasatiempo":"Interior(Cines, en casa, etc.)","personalidad":"Introvertido pero abierto a nuevas experiencias","peliculas":"Star wars","comida":"No tengo preferencia","loteria":"Invertirlo","bebida":"Jugos de fruta","b_alcoholica":"Licores dulces(Jagger, 3 plumas, goss cake, etc)","viaje":"Europa","musica":"Cumbiones\/Nacional","prioridad_pareja":"Dinero\/estatus social","terapia":"Como mis penas","nombre":"9"},{"orientacion":"Homosexual","genero":"Mujer","telefono":1,"mascota":"Mucha responsabilidad","signo":"Capricornio","entretenimiento":"Series","pasatiempo":"Interior(Cines, en casa, etc.)","personalidad":"Introvertido pero abierto a nuevas experiencias","peliculas":"Star wars","comida":"No tengo preferencia","loteria":"Hacer caridad","bebida":"Jugos de fruta","b_alcoholica":"No tomo","viaje":"Africa","musica":"Cumbiones\/Nacional","prioridad_pareja":"Madurez","terapia":"Entretenimiento(Peliculas, series, musica)","nombre":"10"},{"orientacion":"Heterosexual","genero":"Mujer","telefono":1,"mascota":"Gatos","signo":"Leo","entretenimiento":"Peliculas","pasatiempo":"Interior(Cines, en casa, etc.)","personalidad":"Extrovertido pero timido","peliculas":"Piratas del caribe","comida":"Dulces","loteria":"Hacer fiestas grandes","bebida":"Cafe","b_alcoholica":"Cerveza","viaje":"El caribe","musica":"Alternativa\/Indie","prioridad_pareja":"Fisico","terapia":"Entretenimiento(Peliculas, series, musica)","nombre":"11"},{"orientacion":"Homosexual","genero":"Mujer","telefono":1,"mascota":"Mucha responsabilidad","signo":"Acuario","entretenimiento":"Libros","pasatiempo":"Interior(Cines, en casa, etc.)","personalidad":"Introvertido","peliculas":"Star wars","comida":"No tengo preferencia","loteria":"Gastarlo en familia y en ti","bebida":"Jugos de fruta","b_alcoholica":"(Ron, vodka, Tequila, singani) y sus cocteles","viaje":"Estados unidos","musica":"Alternativa\/Indie","prioridad_pareja":"Sentido del humor","terapia":"Entretenimiento(Peliculas, series, musica)","nombre":"12"},{"orientacion":"Heterosexual","genero":"Mujer","telefono":1,"mascota":"Perros","signo":"Virgo","entretenimiento":"Peliculas","pasatiempo":"Interior(Cines, en casa, etc.)","personalidad":"Extrovertido pero timido","peliculas":"Harry potter","comida":"Salado","loteria":"Invertirlo","bebida":"Te","b_alcoholica":"Cerveza","viaje":"Africa","musica":"Alternativa\/Indie","prioridad_pareja":"Dinero\/estatus social","terapia":"Vivo con el dolor","nombre":"13"},{"orientacion":"Heterosexual","genero":"Hombre","telefono":1,"mascota":"Gatos","signo":"Geminis","entretenimiento":"Videojuegos","pasatiempo":"Exterior(Parques, restaurantes, etc.)","personalidad":"Extrovertido","peliculas":"Piratas del caribe","comida":"Dulces","loteria":"Viajar por el mundo","bebida":"Cafe","b_alcoholica":"Vino","viaje":"Estados unidos","musica":"Rock espa\u00f1ol\/ingles","prioridad_pareja":"Limpieza","terapia":"Ejercicio","nombre":"14"},{"orientacion":"Homosexual","genero":"Mujer","telefono":1,"mascota":"Mucha responsabilidad","signo":"Geminis","entretenimiento":"Peliculas","pasatiempo":"Interior(Cines, en casa, etc.)","personalidad":"Extrovertido","peliculas":"Star wars","comida":"No tengo preferencia","loteria":"Viajar por el mundo","bebida":"Jugos de fruta","b_alcoholica":"Vino","viaje":"Asia","musica":"Pop en ingles","prioridad_pareja":"Limpieza","terapia":"Busco alguien para desahogarme","nombre":"15"},{"orientacion":"Homosexual","genero":"Hombre","telefono":1,"mascota":"Mucha responsabilidad","signo":"Piscis","entretenimiento":"Series","pasatiempo":"Exterior(Parques, restaurantes, etc.)","personalidad":"Introvertido","peliculas":"Star wars","comida":"No tengo preferencia","loteria":"Gastarlo en familia y en ti","bebida":"Jugos de fruta","b_alcoholica":"(Ron, vodka, Tequila, singani) y sus cocteles","viaje":"El caribe","musica":"Pop latino\/reguet\u00f3n","prioridad_pareja":"Sentido del humor","terapia":"Vivo con el dolor","nombre":"16"},{"orientacion":"Heterosexual","genero":"Hombre","telefono":1,"mascota":"Perros","signo":"Piscis","entretenimiento":"Peliculas","pasatiempo":"Exterior(Parques, restaurantes, etc.)","personalidad":"Introvertido","peliculas":"Harry potter","comida":"Salado","loteria":"Gastarlo en familia y en ti","bebida":"Te","b_alcoholica":"(Ron, vodka, Tequila, singani) y sus cocteles","viaje":"El caribe","musica":"Rock espa\u00f1ol\/ingles","prioridad_pareja":"Sentido del humor","terapia":"Ejercicio","nombre":"17"},{"orientacion":"Heterosexual","genero":"Hombre","telefono":1,"mascota":"Perros","signo":"Tauro","entretenimiento":"Libros","pasatiempo":"Exterior(Parques, restaurantes, etc.)","personalidad":"Extrovertido","peliculas":"Harry potter","comida":"Salado","loteria":"Viajar por el mundo","bebida":"Te","b_alcoholica":"Guarapo","viaje":"Estados unidos","musica":"Pop en ingles","prioridad_pareja":"Limpieza","terapia":"Ejercicio","nombre":"18"},{"orientacion":"Bisexual","genero":"Hombre","telefono":1,"mascota":"Reptiles","signo":"Sagitario","entretenimiento":"Series","pasatiempo":"Exterior(Parques, restaurantes, etc.)","personalidad":"Introvertido pero abierto a nuevas experiencias","peliculas":"Distopica juvenil(Juegos del hambre, maze runner, etc)","comida":"Ambos juntos","loteria":"Hacer caridad","bebida":"Soda","b_alcoholica":"No tomo","viaje":"Africa","musica":"Pop en ingles","prioridad_pareja":"Madurez","terapia":"Vivo con el dolor","nombre":"19"},{"orientacion":"Heterosexual","genero":"Hombre","telefono":1,"mascota":"Gatos","signo":"Acuario","entretenimiento":"Videojuegos","pasatiempo":"Exterior(Parques, restaurantes, etc.)","personalidad":"Introvertido","peliculas":"Piratas del caribe","comida":"Dulces","loteria":"Gastarlo en familia y en ti","bebida":"Cafe","b_alcoholica":"(Ron, vodka, Tequila, singani) y sus cocteles","viaje":"Europa","musica":"Rock espa\u00f1ol\/ingles","prioridad_pareja":"Sentido del humor","terapia":"Ejercicio","nombre":"20"},{"orientacion":"Homosexual","genero":"Mujer","telefono":1,"mascota":"Mucha responsabilidad","signo":"Capricornio","entretenimiento":"Libros","pasatiempo":"Interior(Cines, en casa, etc.)","personalidad":"Introvertido pero abierto a nuevas experiencias","peliculas":"Star wars","comida":"No tengo preferencia","loteria":"Hacer caridad","bebida":"Jugos de fruta","b_alcoholica":"No tomo","viaje":"Asia","musica":"Pop en ingles","prioridad_pareja":"Madurez","terapia":"Ejercicio","nombre":"21"},{"orientacion":"Heterosexual","genero":"Mujer","telefono":1,"mascota":"Perros","signo":"Capricornio","entretenimiento":"Series","pasatiempo":"Interior(Cines, en casa, etc.)","personalidad":"Introvertido pero abierto a nuevas experiencias","peliculas":"Harry potter","comida":"Salado","loteria":"Hacer caridad","bebida":"Te","b_alcoholica":"No tomo","viaje":"Africa","musica":"Pop en ingles","prioridad_pareja":"Madurez","terapia":"Ejercicio","nombre":"22"},{"orientacion":"Heterosexual","genero":"Mujer","telefono":1,"mascota":"Gatos","signo":"Virgo","entretenimiento":"Videojuegos","pasatiempo":"Interior(Cines, en casa, etc.)","personalidad":"Extrovertido pero timido","peliculas":"Piratas del caribe","comida":"Dulces","loteria":"Invertirlo","bebida":"Cafe","b_alcoholica":"Cerveza","viaje":"Europa","musica":"Pop en ingles","prioridad_pareja":"Dinero\/estatus social","terapia":"Ejercicio","nombre":"23"},{"orientacion":"Heterosexual","genero":"Hombre","telefono":1,"mascota":"Perros","signo":"Virgo","entretenimiento":"Videojuegos","pasatiempo":"Exterior(Parques, restaurantes, etc.)","personalidad":"Extrovertido pero timido","peliculas":"Harry potter","comida":"Salado","loteria":"Invertirlo","bebida":"Te","b_alcoholica":"Cerveza","viaje":"Asia","musica":"Pop en ingles","prioridad_pareja":"Dinero\/estatus social","terapia":"Vivo con el dolor","nombre":"24"},{"orientacion":"Homosexual","genero":"Hombre","telefono":1,"mascota":"Mucha responsabilidad","signo":"Piscis","entretenimiento":"Series","pasatiempo":"Exterior(Parques, restaurantes, etc.)","personalidad":"Introvertido","peliculas":"Star wars","comida":"No tengo preferencia","loteria":"Gastarlo en familia y en ti","bebida":"Jugos de fruta","b_alcoholica":"(Ron, vodka, Tequila, singani) y sus cocteles","viaje":"Africa","musica":"Rock espa\u00f1ol\/ingles","prioridad_pareja":"Sentido del humor","terapia":"Vivo con el dolor","nombre":"25"},{"orientacion":"Heterosexual","genero":"Hombre","telefono":1,"mascota":"Gatos","signo":"Acuario","entretenimiento":"Videojuegos","pasatiempo":"Exterior(Parques, restaurantes, etc.)","personalidad":"Introvertido","peliculas":"Piratas del caribe","comida":"Dulces","loteria":"Gastarlo en familia y en ti","bebida":"Cafe","b_alcoholica":"(Ron, vodka, Tequila, singani) y sus cocteles","viaje":"El caribe","musica":"Rock espa\u00f1ol\/ingles","prioridad_pareja":"Sentido del humor","terapia":"Busco alguien para desahogarme","nombre":"26"},{"orientacion":"Bisexual","genero":"Hombre","telefono":1,"mascota":"Reptiles","signo":"Tauro","entretenimiento":"Series","pasatiempo":"Exterior(Parques, restaurantes, etc.)","personalidad":"Extrovertido","peliculas":"Distopica juvenil(Juegos del hambre, maze runner, etc)","comida":"Ambos juntos","loteria":"Viajar por el mundo","bebida":"Soda","b_alcoholica":"Guarapo","viaje":"Africa","musica":"Pop latino\/reguet\u00f3n","prioridad_pareja":"Limpieza","terapia":"Como mis penas","nombre":"27"},{"orientacion":"Heterosexual","genero":"Mujer","telefono":1,"mascota":"Aves","signo":"Aries","entretenimiento":"Series","pasatiempo":"Interior(Cines, en casa, etc.)","personalidad":"Introvertido","peliculas":"MCU(Marvel)","comida":"Salado","loteria":"Viajar por el mundo","bebida":"Agua","b_alcoholica":"Guarapo","viaje":"Europa","musica":"Cumbiones\/Nacional","prioridad_pareja":"Limpieza","terapia":"Busco alguien para desahogarme","nombre":"28"},{"orientacion":"Homosexual","genero":"Hombre","telefono":1,"mascota":"Mucha responsabilidad","signo":"Cancer","entretenimiento":"Peliculas","pasatiempo":"Exterior(Parques, restaurantes, etc.)","personalidad":"Extrovertido","peliculas":"Star wars","comida":"No tengo preferencia","loteria":"Hacer fiestas grandes","bebida":"Jugos de fruta","b_alcoholica":"Vino","viaje":"El caribe","musica":"Pop latino\/reguet\u00f3n","prioridad_pareja":"Fisico","terapia":"Ejercicio","nombre":"29"},{"orientacion":"Heterosexual","genero":"Mujer","telefono":1,"mascota":"Aves","signo":"Escorpio","entretenimiento":"Libros","pasatiempo":"Interior(Cines, en casa, etc.)","personalidad":"Introvertido pero abierto a nuevas experiencias","peliculas":"MCU(Marvel)","comida":"Ambos juntos","loteria":"Hacer caridad","bebida":"Agua","b_alcoholica":"Licores dulces(Jagger, 3 plumas, goss cake, etc)","viaje":"Estados unidos","musica":"Pop en ingles","prioridad_pareja":"Madurez","terapia":"Busco alguien para desahogarme","nombre":"30"},{"orientacion":"Bisexual","genero":"Hombre","telefono":1,"mascota":"Reptiles","signo":"Acuario","entretenimiento":"Series","pasatiempo":"Exterior(Parques, restaurantes, etc.)","personalidad":"Introvertido","peliculas":"Distopica juvenil(Juegos del hambre, maze runner, etc)","comida":"Ambos juntos","loteria":"Gastarlo en familia y en ti","bebida":"Soda","b_alcoholica":"(Ron, vodka, Tequila, singani) y sus cocteles","viaje":"Europa","musica":"Pop latino\/reguet\u00f3n","prioridad_pareja":"Sentido del humor","terapia":"Entretenimiento(Peliculas, series, musica)","nombre":"31"},{"orientacion":"Homosexual","genero":"Mujer","telefono":1,"mascota":"Reptiles","signo":"Aries","entretenimiento":"Libros","pasatiempo":"Interior(Cines, en casa, etc.)","personalidad":"Introvertido","peliculas":"Distopica juvenil(Juegos del hambre, maze runner, etc)","comida":"No tengo preferencia","loteria":"Viajar por el mundo","bebida":"Soda","b_alcoholica":"Guarapo","viaje":"Europa","musica":"Alternativa\/Indie","prioridad_pareja":"Limpieza","terapia":"Busco alguien para desahogarme","nombre":"32"},{"orientacion":"Heterosexual","genero":"Hombre","telefono":1,"mascota":"Perros","signo":"Piscis","entretenimiento":"Peliculas","pasatiempo":"Exterior(Parques, restaurantes, etc.)","personalidad":"Introvertido","peliculas":"Harry potter","comida":"Salado","loteria":"Gastarlo en familia y en ti","bebida":"Te","b_alcoholica":"(Ron, vodka, Tequila, singani) y sus cocteles","viaje":"Africa","musica":"Pop latino\/reguet\u00f3n","prioridad_pareja":"Sentido del humor","terapia":"Ejercicio","nombre":"33"},{"orientacion":"Heterosexual","genero":"Mujer","telefono":1,"mascota":"Aves","signo":"Capricornio","entretenimiento":"Peliculas","pasatiempo":"Interior(Cines, en casa, etc.)","personalidad":"Introvertido pero abierto a nuevas experiencias","peliculas":"MCU(Marvel)","comida":"Salado","loteria":"Hacer caridad","bebida":"Agua","b_alcoholica":"No tomo","viaje":"Estados unidos","musica":"Pop en ingles","prioridad_pareja":"Madurez","terapia":"Vivo con el dolor","nombre":"34"},{"orientacion":"Heterosexual","genero":"Hombre","telefono":1,"mascota":"Perros","signo":"Cancer","entretenimiento":"Videojuegos","pasatiempo":"Exterior(Parques, restaurantes, etc.)","personalidad":"Extrovertido","peliculas":"Harry potter","comida":"Salado","loteria":"Hacer fiestas grandes","bebida":"Te","b_alcoholica":"Vino","viaje":"Estados unidos","musica":"Rock espa\u00f1ol\/ingles","prioridad_pareja":"Fisico","terapia":"Como mis penas","nombre":"35"},{"orientacion":"Homosexual","genero":"Mujer","telefono":1,"mascota":"Reptiles","signo":"Virgo","entretenimiento":"Libros","pasatiempo":"Interior(Cines, en casa, etc.)","personalidad":"Extrovertido pero timido","peliculas":"Distopica juvenil(Juegos del hambre, maze runner, etc)","comida":"No tengo preferencia","loteria":"Invertirlo","bebida":"Soda","b_alcoholica":"Cerveza","viaje":"Africa","musica":"Cumbiones\/Nacional","prioridad_pareja":"Dinero\/estatus social","terapia":"Entretenimiento(Peliculas, series, musica)","nombre":"36"},{"orientacion":"Heterosexual","genero":"Mujer","telefono":1,"mascota":"Perros","signo":"Leo","entretenimiento":"Series","pasatiempo":"Interior(Cines, en casa, etc.)","personalidad":"Extrovertido pero timido","peliculas":"Harry potter","comida":"Dulces","loteria":"Hacer fiestas grandes","bebida":"Te","b_alcoholica":"Cerveza","viaje":"Africa","musica":"Alternativa\/Indie","prioridad_pareja":"Fisico","terapia":"Como mis penas","nombre":"37"},{"orientacion":"Homosexual","genero":"Mujer","telefono":1,"mascota":"Mucha responsabilidad","signo":"Cancer","entretenimiento":"Peliculas","pasatiempo":"Interior(Cines, en casa, etc.)","personalidad":"Extrovertido","peliculas":"Star wars","comida":"No tengo preferencia","loteria":"Hacer fiestas grandes","bebida":"Jugos de fruta","b_alcoholica":"Vino","viaje":"El caribe","musica":"Cumbiones\/Nacional","prioridad_pareja":"Fisico","terapia":"Entretenimiento(Peliculas, series, musica)","nombre":"38"},{"orientacion":"Homosexual","genero":"Mujer","telefono":1,"mascota":"Mucha responsabilidad","signo":"Geminis","entretenimiento":"Videojuegos","pasatiempo":"Interior(Cines, en casa, etc.)","personalidad":"Extrovertido","peliculas":"Star wars","comida":"No tengo preferencia","loteria":"Viajar por el mundo","bebida":"Jugos de fruta","b_alcoholica":"Vino","viaje":"Estados unidos","musica":"Alternativa\/Indie","prioridad_pareja":"Limpieza","terapia":"Vivo con el dolor","nombre":"39"},{"orientacion":"Heterosexual","genero":"Hombre","telefono":1,"mascota":"Aves","signo":"Geminis","entretenimiento":"Videojuegos","pasatiempo":"Exterior(Parques, restaurantes, etc.)","personalidad":"Extrovertido","peliculas":"MCU(Marvel)","comida":"Salado","loteria":"Viajar por el mundo","bebida":"Agua","b_alcoholica":"Vino","viaje":"Asia","musica":"Rock espa\u00f1ol\/ingles","prioridad_pareja":"Limpieza","terapia":"Como mis penas","nombre":"40"},{"orientacion":"Heterosexual","genero":"Mujer","telefono":1,"mascota":"Perros","signo":"Libra","entretenimiento":"Videojuegos","pasatiempo":"Interior(Cines, en casa, etc.)","personalidad":"Extrovertido pero timido","peliculas":"Harry potter","comida":"Dulces","loteria":"Invertirlo","bebida":"Te","b_alcoholica":"Licores dulces(Jagger, 3 plumas, goss cake, etc)","viaje":"Africa","musica":"Cumbiones\/Nacional","prioridad_pareja":"Dinero\/estatus social","terapia":"Entretenimiento(Peliculas, series, musica)","nombre":"41"},{"orientacion":"Heterosexual","genero":"Mujer","telefono":1,"mascota":"Perros","signo":"Tauro","entretenimiento":"Libros","pasatiempo":"Interior(Cines, en casa, etc.)","personalidad":"Extrovertido","peliculas":"Harry potter","comida":"Salado","loteria":"Viajar por el mundo","bebida":"Te","b_alcoholica":"Guarapo","viaje":"Asia","musica":"Alternativa\/Indie","prioridad_pareja":"Limpieza","terapia":"Como mis penas","nombre":"42"},{"orientacion":"Homosexual","genero":"Mujer","telefono":1,"mascota":"Reptiles","signo":"Aries","entretenimiento":"Videojuegos","pasatiempo":"Interior(Cines, en casa, etc.)","personalidad":"Introvertido","peliculas":"Distopica juvenil(Juegos del hambre, maze runner, etc)","comida":"No tengo preferencia","loteria":"Viajar por el mundo","bebida":"Soda","b_alcoholica":"Guarapo","viaje":"Africa","musica":"Cumbiones\/Nacional","prioridad_pareja":"Limpieza","terapia":"Vivo con el dolor","nombre":"43"},{"orientacion":"Heterosexual","genero":"Hombre","telefono":1,"mascota":"Aves","signo":"Cancer","entretenimiento":"Libros","pasatiempo":"Exterior(Parques, restaurantes, etc.)","personalidad":"Extrovertido","peliculas":"MCU(Marvel)","comida":"Salado","loteria":"Hacer fiestas grandes","bebida":"Agua","b_alcoholica":"Vino","viaje":"Asia","musica":"Rock espa\u00f1ol\/ingles","prioridad_pareja":"Fisico","terapia":"Vivo con el dolor","nombre":"44"},{"orientacion":"Heterosexual","genero":"Hombre","telefono":1,"mascota":"Perros","signo":"Capricornio","entretenimiento":"Peliculas","pasatiempo":"Exterior(Parques, restaurantes, etc.)","personalidad":"Introvertido pero abierto a nuevas experiencias","peliculas":"Harry potter","comida":"Salado","loteria":"Hacer caridad","bebida":"Te","b_alcoholica":"No tomo","viaje":"Africa","musica":"Rock espa\u00f1ol\/ingles","prioridad_pareja":"Madurez","terapia":"Busco alguien para desahogarme","nombre":"45"},{"orientacion":"Heterosexual","genero":"Hombre","telefono":1,"mascota":"Gatos","signo":"Escorpio","entretenimiento":"Peliculas","pasatiempo":"Exterior(Parques, restaurantes, etc.)","personalidad":"Introvertido pero abierto a nuevas experiencias","peliculas":"Piratas del caribe","comida":"Dulces","loteria":"Invertirlo","bebida":"Cafe","b_alcoholica":"Licores dulces(Jagger, 3 plumas, goss cake, etc)","viaje":"Estados unidos","musica":"Pop latino\/reguet\u00f3n","prioridad_pareja":"Dinero\/estatus social","terapia":"Entretenimiento(Peliculas, series, musica)","nombre":"46"},{"orientacion":"Heterosexual","genero":"Mujer","telefono":1,"mascota":"Aves","signo":"Leo","entretenimiento":"Peliculas","pasatiempo":"Interior(Cines, en casa, etc.)","personalidad":"Extrovertido pero timido","peliculas":"MCU(Marvel)","comida":"Ambos juntos","loteria":"Hacer fiestas grandes","bebida":"Agua","b_alcoholica":"Cerveza","viaje":"Estados unidos","musica":"Alternativa\/Indie","prioridad_pareja":"Fisico","terapia":"Ejercicio","nombre":"47"},{"orientacion":"Heterosexual","genero":"Mujer","telefono":1,"mascota":"Gatos","signo":"Escorpio","entretenimiento":"Series","pasatiempo":"Interior(Cines, en casa, etc.)","personalidad":"Introvertido pero abierto a nuevas experiencias","peliculas":"Piratas del caribe","comida":"Dulces","loteria":"Invertirlo","bebida":"Cafe","b_alcoholica":"Licores dulces(Jagger, 3 plumas, goss cake, etc)","viaje":"Estados unidos","musica":"Pop en ingles","prioridad_pareja":"Dinero\/estatus social","terapia":"Entretenimiento(Peliculas, series, musica)","nombre":"48"},{"orientacion":"Heterosexual","genero":"Mujer","telefono":1,"mascota":"Aves","signo":"Acuario","entretenimiento":"Series","pasatiempo":"Interior(Cines, en casa, etc.)","personalidad":"Introvertido","peliculas":"MCU(Marvel)","comida":"Salado","loteria":"Gastarlo en familia y en ti","bebida":"Agua","b_alcoholica":"(Ron, vodka, Tequila, singani) y sus cocteles","viaje":"Europa","musica":"Alternativa\/Indie","prioridad_pareja":"Sentido del humor","terapia":"Entretenimiento(Peliculas, series, musica)","nombre":"49"},{"orientacion":"Heterosexual","genero":"Mujer","telefono":1,"mascota":"Aves","signo":"Capricornio","entretenimiento":"Peliculas","pasatiempo":"Interior(Cines, en casa, etc.)","personalidad":"Introvertido pero abierto a nuevas experiencias","peliculas":"MCU(Marvel)","comida":"Ambos juntos","loteria":"Hacer caridad","bebida":"Agua","b_alcoholica":"No tomo","viaje":"Europa","musica":"Alternativa\/Indie","prioridad_pareja":"Madurez","terapia":"Busco alguien para desahogarme","nombre":"50"},{"orientacion":"Heterosexual","genero":"Hombre","telefono":1,"mascota":"Gatos","signo":"Leo","entretenimiento":"Libros","pasatiempo":"Exterior(Parques, restaurantes, etc.)","personalidad":"Extrovertido pero timido","peliculas":"Piratas del caribe","comida":"Dulces","loteria":"Hacer fiestas grandes","bebida":"Cafe","b_alcoholica":"Cerveza","viaje":"Estados unidos","musica":"Pop latino\/reguet\u00f3n","prioridad_pareja":"Fisico","terapia":"Ejercicio","nombre":"51"},{"orientacion":"Homosexual","genero":"Mujer","telefono":1,"mascota":"Mucha responsabilidad","signo":"Libra","entretenimiento":"Peliculas","pasatiempo":"Interior(Cines, en casa, etc.)","personalidad":"Extrovertido pero timido","peliculas":"Star wars","comida":"No tengo preferencia","loteria":"Invertirlo","bebida":"Jugos de fruta","b_alcoholica":"Licores dulces(Jagger, 3 plumas, goss cake, etc)","viaje":"Africa","musica":"Pop en ingles","prioridad_pareja":"Dinero\/estatus social","terapia":"Busco alguien para desahogarme","nombre":"52"},{"orientacion":"Bisexual","genero":"Hombre","telefono":1,"mascota":"Reptiles","signo":"Piscis","entretenimiento":"Videojuegos","pasatiempo":"Exterior(Parques, restaurantes, etc.)","personalidad":"Introvertido","peliculas":"Distopica juvenil(Juegos del hambre, maze runner, etc)","comida":"Ambos juntos","loteria":"Gastarlo en familia y en ti","bebida":"Soda","b_alcoholica":"(Ron, vodka, Tequila, singani) y sus cocteles","viaje":"Estados unidos","musica":"Pop latino\/reguet\u00f3n","prioridad_pareja":"Sentido del humor","terapia":"Entretenimiento(Peliculas, series, musica)","nombre":"53"},{"orientacion":"Bisexual","genero":"Mujer","telefono":1,"mascota":"Reptiles","signo":"Leo","entretenimiento":"Libros","pasatiempo":"Interior(Cines, en casa, etc.)","personalidad":"Extrovertido pero timido","peliculas":"Distopica juvenil(Juegos del hambre, maze runner, etc)","comida":"Ambos juntos","loteria":"Hacer fiestas grandes","bebida":"Soda","b_alcoholica":"Cerveza","viaje":"Asia","musica":"Alternativa\/Indie","prioridad_pareja":"Fisico","terapia":"Ejercicio","nombre":"54"},{"orientacion":"Heterosexual","genero":"Hombre","telefono":1,"mascota":"Perros","signo":"Virgo","entretenimiento":"Series","pasatiempo":"Exterior(Parques, restaurantes, etc.)","personalidad":"Extrovertido pero timido","peliculas":"Harry potter","comida":"Salado","loteria":"Hacer fiestas grandes","bebida":"Te","b_alcoholica":"Cerveza","viaje":"Africa","musica":"Pop en ingles","prioridad_pareja":"Fisico","terapia":"Vivo con el dolor","nombre":"55"},{"orientacion":"Homosexual","genero":"Hombre","telefono":1,"mascota":"Mucha responsabilidad","signo":"Capricornio","entretenimiento":"Videojuegos","pasatiempo":"Exterior(Parques, restaurantes, etc.)","personalidad":"Introvertido pero abierto a nuevas experiencias","peliculas":"Star wars","comida":"No tengo preferencia","loteria":"Hacer caridad","bebida":"Jugos de fruta","b_alcoholica":"No tomo","viaje":"El caribe","musica":"Rock espa\u00f1ol\/ingles","prioridad_pareja":"Madurez","terapia":"Vivo con el dolor","nombre":"56"},{"orientacion":"Heterosexual","genero":"Hombre","telefono":1,"mascota":"Gatos","signo":"Leo","entretenimiento":"Libros","pasatiempo":"Exterior(Parques, restaurantes, etc.)","personalidad":"Extrovertido pero timido","peliculas":"Piratas del caribe","comida":"Dulces","loteria":"Hacer fiestas grandes","bebida":"Cafe","b_alcoholica":"Cerveza","viaje":"Asia","musica":"Rock espa\u00f1ol\/ingles","prioridad_pareja":"Fisico","terapia":"Como mis penas","nombre":"57"},{"orientacion":"Heterosexual","genero":"Mujer","telefono":1,"mascota":"Perros","signo":"Virgo","entretenimiento":"Series","pasatiempo":"Interior(Cines, en casa, etc.)","personalidad":"Extrovertido pero timido","peliculas":"Harry potter","comida":"Dulces","loteria":"Invertirlo","bebida":"Te","b_alcoholica":"Cerveza","viaje":"Europa","musica":"Cumbiones\/Nacional","prioridad_pareja":"Dinero\/estatus social","terapia":"Como mis penas","nombre":"58"},{"orientacion":"Homosexual","genero":"Mujer","telefono":1,"mascota":"Mucha responsabilidad","signo":"Escorpio","entretenimiento":"Videojuegos","pasatiempo":"Interior(Cines, en casa, etc.)","personalidad":"Introvertido pero abierto a nuevas experiencias","peliculas":"Star wars","comida":"No tengo preferencia","loteria":"Invertirlo","bebida":"Jugos de fruta","b_alcoholica":"Licores dulces(Jagger, 3 plumas, goss cake, etc)","viaje":"El caribe","musica":"Cumbiones\/Nacional","prioridad_pareja":"Dinero\/estatus social","terapia":"Como mis penas","nombre":"59"},{"orientacion":"Homosexual","genero":"Mujer","telefono":1,"mascota":"Reptiles","signo":"Piscis","entretenimiento":"Series","pasatiempo":"Interior(Cines, en casa, etc.)","personalidad":"Introvertido","peliculas":"Distopica juvenil(Juegos del hambre, maze runner, etc)","comida":"No tengo preferencia","loteria":"Gastarlo en familia y en ti","bebida":"Soda","b_alcoholica":"(Ron, vodka, Tequila, singani) y sus cocteles","viaje":"Asia","musica":"Cumbiones\/Nacional","prioridad_pareja":"Sentido del humor","terapia":"Vivo con el dolor","nombre":"60"},{"orientacion":"Heterosexual","genero":"Hombre","telefono":1,"mascota":"Aves","signo":"Sagitario","entretenimiento":"Videojuegos","pasatiempo":"Exterior(Parques, restaurantes, etc.)","personalidad":"Introvertido pero abierto a nuevas experiencias","peliculas":"MCU(Marvel)","comida":"Ambos juntos","loteria":"Hacer caridad","bebida":"Agua","b_alcoholica":"No tomo","viaje":"El caribe","musica":"Rock espa\u00f1ol\/ingles","prioridad_pareja":"Madurez","terapia":"Ejercicio","nombre":"61"},{"orientacion":"Heterosexual","genero":"Hombre","telefono":1,"mascota":"Gatos","signo":"Piscis","entretenimiento":"Series","pasatiempo":"Exterior(Parques, restaurantes, etc.)","personalidad":"Introvertido","peliculas":"Piratas del caribe","comida":"Dulces","loteria":"Gastarlo en familia y en ti","bebida":"Cafe","b_alcoholica":"(Ron, vodka, Tequila, singani) y sus cocteles","viaje":"Asia","musica":"Pop en ingles","prioridad_pareja":"Sentido del humor","terapia":"Busco alguien para desahogarme","nombre":"62"},{"orientacion":"Bisexual","genero":"Hombre","telefono":1,"mascota":"Reptiles","signo":"Sagitario","entretenimiento":"Series","pasatiempo":"Exterior(Parques, restaurantes, etc.)","personalidad":"Introvertido pero abierto a nuevas experiencias","peliculas":"Distopica juvenil(Juegos del hambre, maze runner, etc)","comida":"Ambos juntos","loteria":"Hacer caridad","bebida":"Soda","b_alcoholica":"No tomo","viaje":"El caribe","musica":"Pop latino\/reguet\u00f3n","prioridad_pareja":"Madurez","terapia":"Vivo con el dolor","nombre":"63"},{"orientacion":"Heterosexual","genero":"Hombre","telefono":1,"mascota":"Perros","signo":"Aries","entretenimiento":"Libros","pasatiempo":"Exterior(Parques, restaurantes, etc.)","personalidad":"Introvertido","peliculas":"Harry potter","comida":"Salado","loteria":"Gastarlo en familia y en ti","bebida":"Te","b_alcoholica":"Guarapo","viaje":"El caribe","musica":"Rock espa\u00f1ol\/ingles","prioridad_pareja":"Sentido del humor","terapia":"Vivo con el dolor","nombre":"64"},{"orientacion":"Bisexual","genero":"Hombre","telefono":1,"mascota":"Reptiles","signo":"Aries","entretenimiento":"Libros","pasatiempo":"Exterior(Parques, restaurantes, etc.)","personalidad":"Introvertido","peliculas":"Distopica juvenil(Juegos del hambre, maze runner, etc)","comida":"Ambos juntos","loteria":"Viajar por el mundo","bebida":"Soda","b_alcoholica":"Guarapo","viaje":"Africa","musica":"Rock espa\u00f1ol\/ingles","prioridad_pareja":"Limpieza","terapia":"Como mis penas","nombre":"65"},{"orientacion":"Heterosexual","genero":"Mujer","telefono":1,"mascota":"Aves","signo":"Tauro","entretenimiento":"Libros","pasatiempo":"Interior(Cines, en casa, etc.)","personalidad":"Extrovertido","peliculas":"MCU(Marvel)","comida":"Ambos juntos","loteria":"Viajar por el mundo","bebida":"Agua","b_alcoholica":"Guarapo","viaje":"Europa","musica":"Cumbiones\/Nacional","prioridad_pareja":"Limpieza","terapia":"Como mis penas","nombre":"66"},{"orientacion":"Heterosexual","genero":"Mujer","telefono":1,"mascota":"Aves","signo":"Cancer","entretenimiento":"Peliculas","pasatiempo":"Interior(Cines, en casa, etc.)","personalidad":"Extrovertido","peliculas":"MCU(Marvel)","comida":"Ambos juntos","loteria":"Hacer fiestas grandes","bebida":"Agua","b_alcoholica":"Vino","viaje":"Africa","musica":"Cumbiones\/Nacional","prioridad_pareja":"Fisico","terapia":"Como mis penas","nombre":"67"},{"orientacion":"Heterosexual","genero":"Mujer","telefono":1,"mascota":"Aves","signo":"Escorpio","entretenimiento":"Videojuegos","pasatiempo":"Interior(Cines, en casa, etc.)","personalidad":"Introvertido pero abierto a nuevas experiencias","peliculas":"MCU(Marvel)","comida":"Ambos juntos","loteria":"Hacer caridad","bebida":"Agua","b_alcoholica":"Licores dulces(Jagger, 3 plumas, goss cake, etc)","viaje":"Estados unidos","musica":"Cumbiones\/Nacional","prioridad_pareja":"Madurez","terapia":"Vivo con el dolor","nombre":"68"},{"orientacion":"Heterosexual","genero":"Hombre","telefono":1,"mascota":"Gatos","signo":"Aries","entretenimiento":"Videojuegos","pasatiempo":"Exterior(Parques, restaurantes, etc.)","personalidad":"Introvertido","peliculas":"Piratas del caribe","comida":"Dulces","loteria":"Gastarlo en familia y en ti","bebida":"Cafe","b_alcoholica":"Guarapo","viaje":"Asia","musica":"Rock espa\u00f1ol\/ingles","prioridad_pareja":"Sentido del humor","terapia":"Vivo con el dolor","nombre":"69"},{"orientacion":"Bisexual","genero":"Hombre","telefono":1,"mascota":"Reptiles","signo":"Sagitario","entretenimiento":"Libros","pasatiempo":"Exterior(Parques, restaurantes, etc.)","personalidad":"Introvertido pero abierto a nuevas experiencias","peliculas":"Distopica juvenil(Juegos del hambre, maze runner, etc)","comida":"Ambos juntos","loteria":"Hacer caridad","bebida":"Soda","b_alcoholica":"No tomo","viaje":"Asia","musica":"Rock espa\u00f1ol\/ingles","prioridad_pareja":"Madurez","terapia":"Busco alguien para desahogarme","nombre":"70"},{"orientacion":"Homosexual","genero":"Hombre","telefono":1,"mascota":"Mucha responsabilidad","signo":"Tauro","entretenimiento":"Series","pasatiempo":"Exterior(Parques, restaurantes, etc.)","personalidad":"Extrovertido","peliculas":"Star wars","comida":"No tengo preferencia","loteria":"Viajar por el mundo","bebida":"Jugos de fruta","b_alcoholica":"Guarapo","viaje":"Africa","musica":"Pop latino\/reguet\u00f3n","prioridad_pareja":"Limpieza","terapia":"Como mis penas","nombre":"71"},{"orientacion":"Heterosexual","genero":"Mujer","telefono":1,"mascota":"Gatos","signo":"Acuario","entretenimiento":"Series","pasatiempo":"Interior(Cines, en casa, etc.)","personalidad":"Introvertido","peliculas":"Piratas del caribe","comida":"Dulces","loteria":"Gastarlo en familia y en ti","bebida":"Cafe","b_alcoholica":"(Ron, vodka, Tequila, singani) y sus cocteles","viaje":"El caribe","musica":"Cumbiones\/Nacional","prioridad_pareja":"Sentido del humor","terapia":"Entretenimiento(Peliculas, series, musica)","nombre":"72"},{"orientacion":"Heterosexual","genero":"Mujer","telefono":1,"mascota":"Aves","signo":"Sagitario","entretenimiento":"Peliculas","pasatiempo":"Interior(Cines, en casa, etc.)","personalidad":"Introvertido pero abierto a nuevas experiencias","peliculas":"MCU(Marvel)","comida":"Salado","loteria":"Hacer caridad","bebida":"Agua","b_alcoholica":"No tomo","viaje":"El caribe","musica":"Alternativa\/Indie","prioridad_pareja":"Madurez","terapia":"Busco alguien para desahogarme","nombre":"73"},{"orientacion":"Heterosexual","genero":"Hombre","telefono":1,"mascota":"Perros","signo":"Leo","entretenimiento":"Libros","pasatiempo":"Exterior(Parques, restaurantes, etc.)","personalidad":"Extrovertido pero timido","peliculas":"Harry potter","comida":"Salado","loteria":"Hacer fiestas grandes","bebida":"Te","b_alcoholica":"Cerveza","viaje":"Estados unidos","musica":"Pop latino\/reguet\u00f3n","prioridad_pareja":"Fisico","terapia":"Busco alguien para desahogarme","nombre":"74"},{"orientacion":"Heterosexual","genero":"Hombre","telefono":1,"mascota":"Perros","signo":"Aries","entretenimiento":"Libros","pasatiempo":"Exterior(Parques, restaurantes, etc.)","personalidad":"Introvertido","peliculas":"Harry potter","comida":"Dulces","loteria":"Gastarlo en familia y en ti","bebida":"Te","b_alcoholica":"Guarapo","viaje":"Africa","musica":"Pop latino\/reguet\u00f3n","prioridad_pareja":"Sentido del humor","terapia":"Como mis penas","nombre":"75"},{"orientacion":"Heterosexual","genero":"Mujer","telefono":1,"mascota":"Gatos","signo":"Leo","entretenimiento":"Videojuegos","pasatiempo":"Interior(Cines, en casa, etc.)","personalidad":"Extrovertido pero timido","peliculas":"Piratas del caribe","comida":"Dulces","loteria":"Hacer fiestas grandes","bebida":"Cafe","b_alcoholica":"Cerveza","viaje":"Africa","musica":"Cumbiones\/Nacional","prioridad_pareja":"Fisico","terapia":"Busco alguien para desahogarme","nombre":"76"},{"orientacion":"Heterosexual","genero":"Hombre","telefono":1,"mascota":"Perros","signo":"Virgo","entretenimiento":"Videojuegos","pasatiempo":"Exterior(Parques, restaurantes, etc.)","personalidad":"Extrovertido pero timido","peliculas":"Harry potter","comida":"Salado","loteria":"Invertirlo","bebida":"Te","b_alcoholica":"Cerveza","viaje":"Asia","musica":"Pop latino\/reguet\u00f3n","prioridad_pareja":"Dinero\/estatus social","terapia":"Vivo con el dolor","nombre":"77"},{"orientacion":"Homosexual","genero":"Hombre","telefono":1,"mascota":"Mucha responsabilidad","signo":"Sagitario","entretenimiento":"Series","pasatiempo":"Exterior(Parques, restaurantes, etc.)","personalidad":"Introvertido pero abierto a nuevas experiencias","peliculas":"Star wars","comida":"No tengo preferencia","loteria":"Hacer caridad","bebida":"Jugos de fruta","b_alcoholica":"No tomo","viaje":"Asia","musica":"Rock espa\u00f1ol\/ingles","prioridad_pareja":"Madurez","terapia":"Como mis penas","nombre":"78"},{"orientacion":"Heterosexual","genero":"Mujer","telefono":1,"mascota":"Perros","signo":"Sagitario","entretenimiento":"Series","pasatiempo":"Interior(Cines, en casa, etc.)","personalidad":"Introvertido pero abierto a nuevas experiencias","peliculas":"Harry potter","comida":"Salado","loteria":"Hacer caridad","bebida":"Te","b_alcoholica":"No tomo","viaje":"Europa","musica":"Cumbiones\/Nacional","prioridad_pareja":"Madurez","terapia":"Como mis penas","nombre":"79"},{"orientacion":"Heterosexual","genero":"Mujer","telefono":1,"mascota":"Aves","signo":"Capricornio","entretenimiento":"Series","pasatiempo":"Interior(Cines, en casa, etc.)","personalidad":"Introvertido pero abierto a nuevas experiencias","peliculas":"MCU(Marvel)","comida":"Salado","loteria":"Hacer caridad","bebida":"Agua","b_alcoholica":"No tomo","viaje":"El caribe","musica":"Cumbiones\/Nacional","prioridad_pareja":"Madurez","terapia":"Busco alguien para desahogarme","nombre":"80"},{"orientacion":"Homosexual","genero":"Hombre","telefono":1,"mascota":"Mucha responsabilidad","signo":"Cancer","entretenimiento":"Peliculas","pasatiempo":"Exterior(Parques, restaurantes, etc.)","personalidad":"Extrovertido","peliculas":"Star wars","comida":"No tengo preferencia","loteria":"Hacer fiestas grandes","bebida":"Jugos de fruta","b_alcoholica":"Vino","viaje":"El caribe","musica":"Pop latino\/reguet\u00f3n","prioridad_pareja":"Fisico","terapia":"Ejercicio","nombre":"81"},{"orientacion":"Heterosexual","genero":"Mujer","telefono":1,"mascota":"Gatos","signo":"Leo","entretenimiento":"Libros","pasatiempo":"Interior(Cines, en casa, etc.)","personalidad":"Extrovertido pero timido","peliculas":"Piratas del caribe","comida":"Dulces","loteria":"Hacer fiestas grandes","bebida":"Cafe","b_alcoholica":"Cerveza","viaje":"Estados unidos","musica":"Pop en ingles","prioridad_pareja":"Fisico","terapia":"Como mis penas","nombre":"82"},{"orientacion":"Bisexual","genero":"Mujer","telefono":1,"mascota":"Reptiles","signo":"Tauro","entretenimiento":"Peliculas","pasatiempo":"Interior(Cines, en casa, etc.)","personalidad":"Extrovertido","peliculas":"Distopica juvenil(Juegos del hambre, maze runner, etc)","comida":"Ambos juntos","loteria":"Viajar por el mundo","bebida":"Soda","b_alcoholica":"Guarapo","viaje":"Europa","musica":"Cumbiones\/Nacional","prioridad_pareja":"Limpieza","terapia":"Como mis penas","nombre":"83"},{"orientacion":"Homosexual","genero":"Mujer","telefono":1,"mascota":"Reptiles","signo":"Tauro","entretenimiento":"Peliculas","pasatiempo":"Interior(Cines, en casa, etc.)","personalidad":"Extrovertido","peliculas":"Distopica juvenil(Juegos del hambre, maze runner, etc)","comida":"No tengo preferencia","loteria":"Viajar por el mundo","bebida":"Soda","b_alcoholica":"Guarapo","viaje":"Estados unidos","musica":"Cumbiones\/Nacional","prioridad_pareja":"Limpieza","terapia":"Busco alguien para desahogarme","nombre":"84"},{"orientacion":"Bisexual","genero":"Hombre","telefono":1,"mascota":"Reptiles","signo":"Tauro","entretenimiento":"Series","pasatiempo":"Exterior(Parques, restaurantes, etc.)","personalidad":"Extrovertido","peliculas":"Distopica juvenil(Juegos del hambre, maze runner, etc)","comida":"Ambos juntos","loteria":"Viajar por el mundo","bebida":"Soda","b_alcoholica":"Guarapo","viaje":"Estados unidos","musica":"Pop latino\/reguet\u00f3n","prioridad_pareja":"Limpieza","terapia":"Vivo con el dolor","nombre":"85"},{"orientacion":"Heterosexual","genero":"Hombre","telefono":1,"mascota":"Aves","signo":"Tauro","entretenimiento":"Series","pasatiempo":"Exterior(Parques, restaurantes, etc.)","personalidad":"Extrovertido","peliculas":"MCU(Marvel)","comida":"Ambos juntos","loteria":"Viajar por el mundo","bebida":"Agua","b_alcoholica":"Guarapo","viaje":"Europa","musica":"Rock espa\u00f1ol\/ingles","prioridad_pareja":"Limpieza","terapia":"Entretenimiento(Peliculas, series, musica)","nombre":"86"},{"orientacion":"Homosexual","genero":"Mujer","telefono":1,"mascota":"Mucha responsabilidad","signo":"Libra","entretenimiento":"Videojuegos","pasatiempo":"Interior(Cines, en casa, etc.)","personalidad":"Extrovertido pero timido","peliculas":"Star wars","comida":"No tengo preferencia","loteria":"Invertirlo","bebida":"Jugos de fruta","b_alcoholica":"Licores dulces(Jagger, 3 plumas, goss cake, etc)","viaje":"El caribe","musica":"Alternativa\/Indie","prioridad_pareja":"Dinero\/estatus social","terapia":"Busco alguien para desahogarme","nombre":"87"},{"orientacion":"Heterosexual","genero":"Hombre","telefono":1,"mascota":"Perros","signo":"Cancer","entretenimiento":"Videojuegos","pasatiempo":"Exterior(Parques, restaurantes, etc.)","personalidad":"Extrovertido","peliculas":"Harry potter","comida":"Salado","loteria":"Hacer fiestas grandes","bebida":"Te","b_alcoholica":"Vino","viaje":"Asia","musica":"Pop latino\/reguet\u00f3n","prioridad_pareja":"Fisico","terapia":"Entretenimiento(Peliculas, series, musica)","nombre":"88"},{"orientacion":"Heterosexual","genero":"Mujer","telefono":1,"mascota":"Aves","signo":"Geminis","entretenimiento":"Videojuegos","pasatiempo":"Interior(Cines, en casa, etc.)","personalidad":"Extrovertido","peliculas":"MCU(Marvel)","comida":"Ambos juntos","loteria":"Viajar por el mundo","bebida":"Agua","b_alcoholica":"Vino","viaje":"Asia","musica":"Alternativa\/Indie","prioridad_pareja":"Limpieza","terapia":"Como mis penas","nombre":"89"},{"orientacion":"Heterosexual","genero":"Mujer","telefono":1,"mascota":"Perros","signo":"Sagitario","entretenimiento":"Series","pasatiempo":"Interior(Cines, en casa, etc.)","personalidad":"Introvertido pero abierto a nuevas experiencias","peliculas":"Harry potter","comida":"Salado","loteria":"Hacer caridad","bebida":"Te","b_alcoholica":"No tomo","viaje":"Asia","musica":"Cumbiones\/Nacional","prioridad_pareja":"Madurez","terapia":"Vivo con el dolor","nombre":"90"},{"orientacion":"Heterosexual","genero":"Hombre","telefono":1,"mascota":"Perros","signo":"Virgo","entretenimiento":"Videojuegos","pasatiempo":"Exterior(Parques, restaurantes, etc.)","personalidad":"Extrovertido pero timido","peliculas":"Harry potter","comida":"Salado","loteria":"Hacer fiestas grandes","bebida":"Te","b_alcoholica":"Cerveza","viaje":"El caribe","musica":"Rock espa\u00f1ol\/ingles","prioridad_pareja":"Fisico","terapia":"Como mis penas","nombre":"91"},{"orientacion":"Heterosexual","genero":"Mujer","telefono":1,"mascota":"Aves","signo":"Capricornio","entretenimiento":"Peliculas","pasatiempo":"Interior(Cines, en casa, etc.)","personalidad":"Introvertido pero abierto a nuevas experiencias","peliculas":"MCU(Marvel)","comida":"Ambos juntos","loteria":"Hacer caridad","bebida":"Agua","b_alcoholica":"No tomo","viaje":"Asia","musica":"Cumbiones\/Nacional","prioridad_pareja":"Madurez","terapia":"Busco alguien para desahogarme","nombre":"92"},{"orientacion":"Homosexual","genero":"Hombre","telefono":1,"mascota":"Mucha responsabilidad","signo":"Virgo","entretenimiento":"Peliculas","pasatiempo":"Exterior(Parques, restaurantes, etc.)","personalidad":"Extrovertido pero timido","peliculas":"Star wars","comida":"No tengo preferencia","loteria":"Invertirlo","bebida":"Jugos de fruta","b_alcoholica":"Cerveza","viaje":"Estados unidos","musica":"Pop latino\/reguet\u00f3n","prioridad_pareja":"Dinero\/estatus social","terapia":"Como mis penas","nombre":"93"},{"orientacion":"Heterosexual","genero":"Mujer","telefono":1,"mascota":"Perros","signo":"Escorpio","entretenimiento":"Videojuegos","pasatiempo":"Interior(Cines, en casa, etc.)","personalidad":"Introvertido pero abierto a nuevas experiencias","peliculas":"Harry potter","comida":"Dulces","loteria":"Hacer caridad","bebida":"Te","b_alcoholica":"Licores dulces(Jagger, 3 plumas, goss cake, etc)","viaje":"El caribe","musica":"Cumbiones\/Nacional","prioridad_pareja":"Madurez","terapia":"Ejercicio","nombre":"94"},{"orientacion":"Heterosexual","genero":"Hombre","telefono":1,"mascota":"Gatos","signo":"Capricornio","entretenimiento":"Videojuegos","pasatiempo":"Exterior(Parques, restaurantes, etc.)","personalidad":"Introvertido pero abierto a nuevas experiencias","peliculas":"Piratas del caribe","comida":"Dulces","loteria":"Hacer caridad","bebida":"Cafe","b_alcoholica":"No tomo","viaje":"Asia","musica":"Pop en ingles","prioridad_pareja":"Madurez","terapia":"Vivo con el dolor","nombre":"95"},{"orientacion":"Heterosexual","genero":"Hombre","telefono":1,"mascota":"Perros","signo":"Tauro","entretenimiento":"Peliculas","pasatiempo":"Exterior(Parques, restaurantes, etc.)","personalidad":"Extrovertido","peliculas":"Harry potter","comida":"Dulces","loteria":"Viajar por el mundo","bebida":"Te","b_alcoholica":"Guarapo","viaje":"Asia","musica":"Rock espa\u00f1ol\/ingles","prioridad_pareja":"Limpieza","terapia":"Vivo con el dolor","nombre":"96"}]